RRD/__init__.py
RRD/bde.py
RRD/bond.py
RRD/pchem.py
RRD/pre_comp.py
RRD/qm.py
RRD/rrd.py
RRD/sterics.py
RRD/bv_model/__init__.py
RRD/bv_model/_train.py
RRD/bv_model/data.py
RRD/bv_model/featurizer.py
RRD/bv_model/model.py
RRD/bv_model/predict.py
RRD/bv_model/trained_model/model_1.pth
RRD/bv_model/trained_model/model_2.pth
RRD/bv_model/trained_model/model_3.pth
RRD/bv_model/trained_model/model_4.pth
RRD/bv_model/trained_model/model_5.pth
RRD-1.1.1.dist-info/METADATA
RRD-1.1.1.dist-info/WHEEL
RRD-1.1.1.dist-info/top_level.txt
RRD-1.1.1.dist-info/RECORD
