Metadata-Version: 2.1
Name: RRD
Version: 1.1.1
Summary: RRD: A Reactivity-Related bond/atom-wise Descriptors (RRD) package
Home-page: https://github.com/AireSxc/AI-Rex-main/tree/main/RRD
Author: WanXiang Shen
License: UNKNOWN
Platform: UNKNOWN
Requires-Dist: torch (==1.10.0+cu113)
Requires-Dist: numpy (==1.21.5)
Requires-Dist: pandas (==1.1.5)
Requires-Dist: qmdesc (==1.0.6)
Requires-Dist: alfabet (==0.3.1)
Requires-Dist: scipy (==1.8.0)
Provides-Extra: dev
Requires-Dist: pytest ; extra == 'dev'
